hypergptsdk/__init__.py
hypergptsdk/hypergptsdk.py
hypergptsdk-0.2.dist-info/LICENSE
hypergptsdk-0.2.dist-info/METADATA
hypergptsdk-0.2.dist-info/WHEEL
hypergptsdk-0.2.dist-info/top_level.txt
hypergptsdk-0.2.dist-info/RECORD
