Metadata-Version: 2.1
Name: hypergptsdk
Version: 0.2
License-File: LICENSE
Requires-Dist: requests
